climxtract/__init__.py
climxtract/ch2025_download.py
climxtract/cordex_download.py
climxtract/desp-authentication.py
climxtract/destine_download.py
climxtract/dictionary.py
climxtract/eobs_download.py
climxtract/era5_download.py
climxtract/healpix_grid.txt
climxtract/mask.py
climxtract/oeks15_download.py
climxtract/oeks15_grid.txt
climxtract/regrid.py
climxtract/spartacus_download.py
climxtract/spartacus_grid.txt
climxtract-1.1.3.dist-info/licenses/LICENSE
climxtract-1.1.3.dist-info/METADATA
climxtract-1.1.3.dist-info/WHEEL
climxtract-1.1.3.dist-info/top_level.txt
climxtract-1.1.3.dist-info/RECORD
